{"py/object": "rasa_core.featurizers.MaxHistoryTrackerFeaturizer", "max_history": 5, "remove_duplicates": true, "state_featurizer": {"py/object": "rasa_core.featurizers.BinarySingleStateFeaturizer", "input_state_map": {"entity_city": 5, "intent_ask_weather": 0, "intent_greet": 1, "intent_mood_happy": 2, "intent_mood_unhappy": 3, "intent_weather_state": 4, "prev_action_ask_weather": 17, "prev_action_deactivate_form": 10, "prev_action_default_ask_affirmation": 12, "prev_action_default_ask_rephrase": 13, "prev_action_default_fallback": 9, "prev_action_listen": 7, "prev_action_restart": 8, "prev_action_revert_fallback_events": 11, "prev_utter_greet": 14, "prev_utter_happy": 15, "prev_utter_unhappy": 16, "prev_utter_weather_good": 18, "slot_city_0": 6}, "num_features": 19, "slot_feature_len": 1, "user_feature_len": 6}, "use_intent_probabilities": false}